pycarbonsh/__init__.py
pycarbonsh/exceptions.py
pycarbonsh/main.py
pycarbonsh-0.1.3.dist-info/LICENSE
pycarbonsh-0.1.3.dist-info/METADATA
pycarbonsh-0.1.3.dist-info/WHEEL
pycarbonsh-0.1.3.dist-info/top_level.txt
pycarbonsh-0.1.3.dist-info/RECORD
