Metadata-Version: 2.1
Name: pycarbonsh
Version: 0.1.3
Summary: The Asynchronous web-scraper for carbon.now.sh which helps to create and share beautiful pics of your code!
Home-page: https://github.com/Pranav-Saxena/PyCarbonSh
Author: Pranav Saxena
License: MIT
Project-URL: Documentation, https://pycarbonsh.readthedocs.io/en/latest/
Project-URL: Issue tracker, https://github.com/Pranav-Saxena/PyCarbonSh/issues
Platform: UNKNOWN
Classifier: Development Status :: 5 - Production/Stable
Classifier: License :: OSI Approved :: MIT License
Classifier: Intended Audience :: Developers
Classifier: Natural Language :: English
Classifier: Operating System :: OS Independent
Classifier: Programming Language :: Python :: 3.8
Classifier: Programming Language :: Python :: 3.9
Classifier: Topic :: Internet
Classifier: Topic :: Software Development :: Libraries
Classifier: Topic :: Software Development :: Libraries :: Python Modules
Requires-Python: >=3.8.0
License-File: LICENSE
Requires-Dist: pyppeteer
Requires-Dist: asyncio
Provides-Extra: docs
Requires-Dist: sphinx (==4.0.2) ; extra == 'docs'
Requires-Dist: sphinxcontrib-trio (==1.1.2) ; extra == 'docs'
Requires-Dist: sphinxcontrib-napoleon ; extra == 'docs'
Requires-Dist: sphinxcontrib-websupport ; extra == 'docs'
Provides-Extra: speed
Requires-Dist: orjson (>=3.5.4) ; extra == 'speed'
